gammatone/__init__.py
gammatone/fftweight.py
gammatone/filters.py
gammatone/gtgram.py
gammatone/plot.py
melizalab_gammatone-0.1.1.dist-info/COPYING
melizalab_gammatone-0.1.1.dist-info/METADATA
melizalab_gammatone-0.1.1.dist-info/WHEEL
melizalab_gammatone-0.1.1.dist-info/top_level.txt
melizalab_gammatone-0.1.1.dist-info/RECORD
