Metadata-Version: 2.1
Name: melizalab-gammatone
Version: 0.1.1
Summary: Gammatone filterbank
Home-page: https://github.com/melizalab/melizalab-gammatone
Author: Dan Meliza
Author-email: dan@meliza.org
Maintainer: Dan Meliza
Maintainer-email: dan@meliza.org
License: BSD 3-Clause License
Keywords: one,two
Classifier: License :: OSI Approved :: BSD License
Classifier: Programming Language :: Python :: 3
Classifier: Programming Language :: Python :: 3.8
Requires-Python: >=3.7
License-File: COPYING
Requires-Dist: numpy (>=1.23.1)
Requires-Dist: scipy (>=1.7.3)
